rbgame/__init__.py
rbgame/menu.py
rbgame/trainer.py
rbgame/utils.py
rbgame/agent/__init__.py
rbgame/agent/astar_agent.py
rbgame/agent/base_agent.py
rbgame/agent/rl_agent.py
rbgame/assets/csv_files/colors_map.csv
rbgame/assets/csv_files/targets_map.csv
rbgame/assets/images/blue_robot.png
rbgame/assets/images/green_robot.png
rbgame/assets/images/loading_bar_background.png
rbgame/assets/images/mail.png
rbgame/assets/images/orange_robot.png
rbgame/assets/images/pink_robot.png
rbgame/assets/images/purple_robot.png
rbgame/assets/images/red_robot.png
rbgame/game/__init__.py
rbgame/game/components.py
rbgame/game/consts.py
rbgame/game/game.py
rbgame-0.0.3.dist-info/LICENSE.md
rbgame-0.0.3.dist-info/METADATA
rbgame-0.0.3.dist-info/WHEEL
rbgame-0.0.3.dist-info/top_level.txt
rbgame-0.0.3.dist-info/RECORD
