Metadata-Version: 2.1
Name: rbgame
Version: 0.0.3
Summary: Board game simulator.
Author-email: Nguyen Thanh Trung <nguyenthanhtrung291099@gmail.com>
License:                     GNU GENERAL PUBLIC LICENSE
Project-URL: Documentation, https://robotic-board-game.readthedocs.io/en/latest/
Project-URL: Repository, https://github.com/nguyenthanhtrung2910/robotic-board-game.git
Keywords: board game,multiagentRL,astar,simulator
Classifier: Development Status :: 2 - Pre-Alpha
Classifier: Intended Audience :: Developers
Classifier: Topic :: Games/Entertainment :: Board Games
Classifier: Topic :: Games/Entertainment :: Simulation
Classifier: License :: OSI Approved :: GNU General Public License v3 (GPLv3)
Classifier: Operating System :: OS Independent
Classifier: Programming Language :: Python :: 3.10
Classifier: Programming Language :: Python :: 3.11
Classifier: Programming Language :: Python :: 3.12
Requires-Python: >=3.10
License-File: LICENSE.md
Requires-Dist: tianshou>=0.5.1
Requires-Dist: pygame>=2.6.1
Requires-Dist: pygame-menu>=4.4.8
Requires-Dist: pyyaml>=6.0.2
Requires-Dist: matplotlib>=3.8.0
Provides-Extra: docs
Requires-Dist: sphinx; extra == "docs"
Requires-Dist: sphinx-autodoc-typehints; extra == "docs"
Requires-Dist: sphinx-rtd-theme; extra == "docs"
